<?xml version="1.0" encoding="utf-8"?>
<ClusterController>
  <Info>
    <Created>2023-11-24T08:10:00</Created>
    <Culture>en</Culture>
    <UtcOffset>-480</UtcOffset>
    <DST>False</DST>
    <FW-Version>1.05.01.4</FW-Version>
  </Info>
  <CurrentPublic>
    <Key>Cluster Controller:165012367:Metering.TotWhOut</Key>
    <Mean>357182.2</Mean>
    <Base>1</Base>
    <Period>300</Period>
    <Timestamp>2023-11-24T08:10:00</Timestamp>
  </CurrentPublic>
  <CurrentPublic>
    <Key>Cluster Controller:165012367:Operation.GriSwCnt</Key>
    <Mean>5234</Mean>
    <Base>1</Base>
    <Period>300</Period>
    <Timestamp>2023-11-24T08:10:00</Timestamp>
  </CurrentPublic>
  <CurrentPublic>
    <Key>Cluster Controller:165012367:Metering.TotOpTms</Key>
    <Mean>58113.64</Mean>
    <Base>1</Base>
    <Period>300</Period>
    <Timestamp>2023-11-24T08:10:00</Timestamp>
  </CurrentPublic>
  <CurrentPublic>
    <Key>SN: 191240180 (SN: 191240180):191240180:Metering.TotWhOut</Key>
    <Mean>118939.4</Mean>
    <Base>1</Base>
    <Period>300</Period>
    <Timestamp>2023-11-24T08:10:00</Timestamp>
  </CurrentPublic>
  <CurrentPublic>
    <Key>SN: 191240180 (SN: 191240180):191240180:Operation.GriSwCnt</Key>
    <Mean>2515</Mean>
    <Base>1</Base>
    <Period>300</Period>
    <Timestamp>2023-11-24T08:10:00</Timestamp>
  </CurrentPublic>
  <CurrentPublic>
    <Key>SN: 191240180 (SN: 191240180):191240180:Metering.TotOpTms</Key>
    <Mean>27254.43</Mean>
    <Base>1</Base>
    <Period>300</Period>
    <Timestamp>2023-11-24T08:10:00</Timestamp>
  </CurrentPublic>
  <CurrentPublic>
    <Key>SN: 191240234 (SN: 191240234):191240234:Metering.TotWhOut</Key>
    <Mean>203621.3</Mean>
    <Base>1</Base>
    <Period>300</Period>
    <Timestamp>2023-11-24T08:10:00</Timestamp>
  </CurrentPublic>
  <CurrentPublic>
    <Key>SN: 191240234 (SN: 191240234):191240234:Operation.GriSwCnt</Key>
    <Mean>2451</Mean>
    <Base>1</Base>
    <Period>300</Period>
    <Timestamp>2023-11-24T08:10:00</Timestamp>
  </CurrentPublic>
  <CurrentPublic>
    <Key>SN: 191240234 (SN: 191240234):191240234:Metering.TotOpTms</Key>
    <Mean>27507.19</Mean>
    <Base>1</Base>
    <Period>300</Period>
    <Timestamp>2023-11-24T08:10:00</Timestamp>
  </CurrentPublic>
  <CurrentPublic>
    <Key>SN: 191246219 (SN: 191246219):191246219:Metering.TotWhOut</Key>
    <Mean>34621.45</Mean>
    <Base>1</Base>
    <Period>300</Period>
    <Timestamp>2023-11-24T08:10:00</Timestamp>
  </CurrentPublic>
  <CurrentPublic>
    <Key>SN: 191246219 (SN: 191246219):191246219:Operation.GriSwCnt</Key>
    <Mean>268</Mean>
    <Base>1</Base>
    <Period>300</Period>
    <Timestamp>2023-11-24T08:10:00</Timestamp>
  </CurrentPublic>
  <CurrentPublic>
    <Key>SN: 191246219 (SN: 191246219):191246219:Metering.TotOpTms</Key>
    <Mean>3352.021</Mean>
    <Base>1</Base>
    <Period>300</Period>
    <Timestamp>2023-11-24T08:10:00</Timestamp>
  </CurrentPublic>
  <CurrentPublic>
    <Key>Cluster Controller:165012367:Metering.TotFeedTms</Key>
    <Mean>56843.71</Mean>
    <Base>1</Base>
    <Period>300</Period>
    <Timestamp>2023-11-24T08:10:00</Timestamp>
  </CurrentPublic>
  <CurrentPublic>
    <Key>SN: 191240180 (SN: 191240180):191240180:Metering.TotFeedTms</Key>
    <Mean>26496.1</Mean>
    <Base>1</Base>
    <Period>300</Period>
    <Timestamp>2023-11-24T08:10:00</Timestamp>
  </CurrentPublic>
  <CurrentPublic>
    <Key>SN: 191240180 (SN: 191240180):191240180:Metering.GridMs.TotWhOut</Key>
    <Mean>1.844674E+16</Mean>
    <Base>1</Base>
    <Period>300</Period>
    <Timestamp>2023-11-24T08:10:00</Timestamp>
  </CurrentPublic>
  <CurrentPublic>
    <Key>SN: 191240234 (SN: 191240234):191240234:Metering.TotFeedTms</Key>
    <Mean>27057.16</Mean>
    <Base>1</Base>
    <Period>300</Period>
    <Timestamp>2023-11-24T08:10:00</Timestamp>
  </CurrentPublic>
  <CurrentPublic>
    <Key>SN: 191240234 (SN: 191240234):191240234:Metering.GridMs.TotWhOut</Key>
    <Mean>1.844674E+16</Mean>
    <Base>1</Base>
    <Period>300</Period>
    <Timestamp>2023-11-24T08:10:00</Timestamp>
  </CurrentPublic>
  <CurrentPublic>
    <Key>SN: 191246219 (SN: 191246219):191246219:Metering.TotFeedTms</Key>
    <Mean>3290.457</Mean>
    <Base>1</Base>
    <Period>300</Period>
    <Timestamp>2023-11-24T08:10:00</Timestamp>
  </CurrentPublic>
  <CurrentPublic>
    <Key>SN: 191246219 (SN: 191246219):191246219:Metering.GridMs.TotWhOut</Key>
    <Mean>1.844674E+16</Mean>
    <Base>1</Base>
    <Period>300</Period>
    <Timestamp>2023-11-24T08:10:00</Timestamp>
  </CurrentPublic>
  <MeanPublic>
    <Key>Cluster Controller:165012367:GridMs.TotW</Key>
    <Min>1033</Min>
    <Max>4127</Max>
    <Mean>6548</Mean>
    <Base>1</Base>
    <Period>300</Period>
    <Timestamp>2023-11-24T08:10:00</Timestamp>
  </MeanPublic>
  <MeanPublic>
    <Key>Cluster Controller:165012367:GridMs.Hz</Key>
    <Min>60.02</Min>
    <Max>60.05</Max>
    <Mean>60.03</Mean>
    <Base>1</Base>
    <Period>300</Period>
    <Timestamp>2023-11-24T08:10:00</Timestamp>
  </MeanPublic>
  <MeanPublic>
    <Key>SN: 191240180 (SN: 191240180):191240180:GridMs.TotW</Key>
    <Min>1033</Min>
    <Max>2313</Max>
    <Mean>1725</Mean>
    <Base>1</Base>
    <Period>300</Period>
    <Timestamp>2023-11-24T08:10:00</Timestamp>
  </MeanPublic>
  <MeanPublic>
    <Key>SN: 191240180 (SN: 191240180):191240180:GridMs.Hz</Key>
    <Min>60.02</Min>
    <Max>60.04</Max>
    <Mean>60.03</Mean>
    <Base>1</Base>
    <Period>300</Period>
    <Timestamp>2023-11-24T08:10:00</Timestamp>
  </MeanPublic>
  <MeanPublic>
    <Key>SN: 191240234 (SN: 191240234):191240234:GridMs.TotW</Key>
    <Min>1074</Min>
    <Max>1691</Max>
    <Mean>1531</Mean>
    <Base>1</Base>
    <Period>300</Period>
    <Timestamp>2023-11-24T08:10:00</Timestamp>
  </MeanPublic>
  <MeanPublic>
    <Key>SN: 191240234 (SN: 191240234):191240234:GridMs.Hz</Key>
    <Min>60.02</Min>
    <Max>60.04</Max>
    <Mean>60.03</Mean>
    <Base>1</Base>
    <Period>300</Period>
    <Timestamp>2023-11-24T08:10:00</Timestamp>
  </MeanPublic>
  <MeanPublic>
    <Key>SN: 191246219 (SN: 191246219):191246219:GridMs.TotW</Key>
    <Min>2184</Min>
    <Max>4127</Max>
    <Mean>3292</Mean>
    <Base>1</Base>
    <Period>300</Period>
    <Timestamp>2023-11-24T08:10:00</Timestamp>
  </MeanPublic>
  <MeanPublic>
    <Key>SN: 191246219 (SN: 191246219):191246219:GridMs.Hz</Key>
    <Min>60.02</Min>
    <Max>60.05</Max>
    <Mean>60.04</Mean>
    <Base>1</Base>
    <Period>300</Period>
    <Timestamp>2023-11-24T08:10:00</Timestamp>
  </MeanPublic>
  <CurrentPublic>
    <Key>Cluster Controller:165012367:Isolation.FltA</Key>
    <Min>18</Min>
    <Max>19</Max>
    <Mean>18</Mean>
    <Base>1</Base>
    <Period>300</Period>
    <Timestamp>2023-11-24T08:10:00</Timestamp>
  </CurrentPublic>
  <CurrentPublic>
    <Key>SN: 191240180 (SN: 191240180):191240180:Isolation.FltA</Key>
    <Min>18</Min>
    <Max>18</Max>
    <Mean>18</Mean>
    <Base>1</Base>
    <Period>300</Period>
    <Timestamp>2023-11-24T08:10:00</Timestamp>
  </CurrentPublic>
  <CurrentPublic>
    <Key>SN: 191240234 (SN: 191240234):191240234:Isolation.FltA</Key>
    <Min>19</Min>
    <Max>19</Max>
    <Mean>19</Mean>
    <Base>1</Base>
    <Period>300</Period>
    <Timestamp>2023-11-24T08:10:00</Timestamp>
  </CurrentPublic>
  <CurrentPublic>
    <Key>SN: 191246219 (SN: 191246219):191246219:Isolation.FltA</Key>
    <Min>18</Min>
    <Max>18</Max>
    <Mean>18</Mean>
    <Base>1</Base>
    <Period>300</Period>
    <Timestamp>2023-11-24T08:10:00</Timestamp>
  </CurrentPublic>
  <CurrentPublic>
    <Key>Cluster Controller:165012367:Isolation.LeakRis</Key>
    <Min>626.809</Min>
    <Max>2565.516</Max>
    <Mean>1377.233</Mean>
    <Base>1</Base>
    <Period>300</Period>
    <Timestamp>2023-11-24T08:10:00</Timestamp>
  </CurrentPublic>
  <CurrentPublic>
    <Key>SN: 191240180 (SN: 191240180):191240180:Isolation.LeakRis</Key>
    <Min>2565.516</Min>
    <Max>2565.516</Max>
    <Mean>2565.516</Mean>
    <Base>1</Base>
    <Period>300</Period>
    <Timestamp>2023-11-24T08:10:00</Timestamp>
  </CurrentPublic>
  <CurrentPublic>
    <Key>SN: 191240234 (SN: 191240234):191240234:Isolation.LeakRis</Key>
    <Min>939.375</Min>
    <Max>939.375</Max>
    <Mean>939.375</Mean>
    <Base>1</Base>
    <Period>300</Period>
    <Timestamp>2023-11-24T08:10:00</Timestamp>
  </CurrentPublic>
  <CurrentPublic>
    <Key>SN: 191246219 (SN: 191246219):191246219:Isolation.LeakRis</Key>
    <Min>626.809</Min>
    <Max>626.809</Max>
    <Mean>626.809</Mean>
    <Base>1</Base>
    <Period>300</Period>
    <Timestamp>2023-11-24T08:10:00</Timestamp>
  </CurrentPublic>
  <MeanPublic>
    <Key>Cluster Controller:165012367:DcMs.Vol[A]</Key>
    <Min>232.21</Min>
    <Max>665.85</Max>
    <Mean>582.52</Mean>
    <Base>1</Base>
    <Period>300</Period>
    <Timestamp>2023-11-24T08:10:00</Timestamp>
  </MeanPublic>
  <MeanPublic>
    <Key>Cluster Controller:165012367:DcMs.Vol[B]</Key>
    <Min>209.63</Min>
    <Max>660.32</Max>
    <Mean>584.65</Mean>
    <Base>1</Base>
    <Period>300</Period>
    <Timestamp>2023-11-24T08:10:00</Timestamp>
  </MeanPublic>
  <MeanPublic>
    <Key>SN: 191240180 (SN: 191240180):191240180:DcMs.Vol[A]</Key>
    <Min>434.24</Min>
    <Max>551.97</Max>
    <Mean>534.34</Mean>
    <Base>1</Base>
    <Period>300</Period>
    <Timestamp>2023-11-24T08:10:00</Timestamp>
  </MeanPublic>
  <MeanPublic>
    <Key>SN: 191240180 (SN: 191240180):191240180:DcMs.Vol[B]</Key>
    <Min>239.65</Min>
    <Max>533.57</Max>
    <Mean>517.34</Mean>
    <Base>1</Base>
    <Period>300</Period>
    <Timestamp>2023-11-24T08:10:00</Timestamp>
  </MeanPublic>
  <MeanPublic>
    <Key>SN: 191240234 (SN: 191240234):191240234:DcMs.Vol[A]</Key>
    <Min>232.21</Min>
    <Max>641.55</Max>
    <Mean>628.75</Mean>
    <Base>1</Base>
    <Period>300</Period>
    <Timestamp>2023-11-24T08:10:00</Timestamp>
  </MeanPublic>
  <MeanPublic>
    <Key>SN: 191240234 (SN: 191240234):191240234:DcMs.Vol[B]</Key>
    <Min>209.63</Min>
    <Max>660.32</Max>
    <Mean>639.97</Mean>
    <Base>1</Base>
    <Period>300</Period>
    <Timestamp>2023-11-24T08:10:00</Timestamp>
  </MeanPublic>
  <MeanPublic>
    <Key>SN: 191246219 (SN: 191246219):191246219:DcMs.Vol[A]</Key>
    <Min>403.05</Min>
    <Max>665.85</Max>
    <Mean>584.47</Mean>
    <Base>1</Base>
    <Period>300</Period>
    <Timestamp>2023-11-24T08:10:00</Timestamp>
  </MeanPublic>
  <MeanPublic>
    <Key>SN: 191246219 (SN: 191246219):191246219:DcMs.Vol[B]</Key>
    <Min>335.37</Min>
    <Max>615.4</Max>
    <Mean>596.65</Mean>
    <Base>1</Base>
    <Period>300</Period>
    <Timestamp>2023-11-24T08:10:00</Timestamp>
  </MeanPublic>
  <MeanPublic>
    <Key>Cluster Controller:165012367:DcMs.Amp[A]</Key>
    <Min>0.972000059326176</Min>
    <Max>3.15400019250489</Max>
    <Mean>1.73300010577393</Mean>
    <Base>1</Base>
    <Period>300</Period>
    <Timestamp>2023-11-24T08:10:00</Timestamp>
  </MeanPublic>
  <MeanPublic>
    <Key>Cluster Controller:165012367:DcMs.Amp[B]</Key>
    <Min>0.952000058105472</Min>
    <Max>4.38700026776125</Max>
    <Mean>2.0250001235962</Mean>
    <Base>1</Base>
    <Period>300</Period>
    <Timestamp>2023-11-24T08:10:00</Timestamp>
  </MeanPublic>
  <MeanPublic>
    <Key>SN: 191240180 (SN: 191240180):191240180:DcMs.Amp[A]</Key>
    <Min>0.972000059326176</Min>
    <Max>2.17500013275147</Max>
    <Mean>1.63200009960938</Mean>
    <Base>1</Base>
    <Period>300</Period>
    <Timestamp>2023-11-24T08:10:00</Timestamp>
  </MeanPublic>
  <MeanPublic>
    <Key>SN: 191240180 (SN: 191240180):191240180:DcMs.Amp[B]</Key>
    <Min>0.952000058105472</Min>
    <Max>2.35700014385987</Max>
    <Mean>1.63300009967042</Mean>
    <Base>1</Base>
    <Period>300</Period>
    <Timestamp>2023-11-24T08:10:00</Timestamp>
  </MeanPublic>
  <MeanPublic>
    <Key>SN: 191240234 (SN: 191240234):191240234:DcMs.Amp[A]</Key>
    <Min>1.11000006774903</Min>
    <Max>1.46700008953858</Max>
    <Mean>1.22900007501221</Mean>
    <Base>1</Base>
    <Period>300</Period>
    <Timestamp>2023-11-24T08:10:00</Timestamp>
  </MeanPublic>
  <MeanPublic>
    <Key>SN: 191240234 (SN: 191240234):191240234:DcMs.Amp[B]</Key>
    <Min>1.04400006372071</Min>
    <Max>2.389000145813</Max>
    <Mean>1.17100007147217</Mean>
    <Base>1</Base>
    <Period>300</Period>
    <Timestamp>2023-11-24T08:10:00</Timestamp>
  </MeanPublic>
  <MeanPublic>
    <Key>SN: 191246219 (SN: 191246219):191246219:DcMs.Amp[A]</Key>
    <Min>2.1730001326294</Min>
    <Max>3.15400019250489</Max>
    <Mean>2.34000014282227</Mean>
    <Base>1</Base>
    <Period>300</Period>
    <Timestamp>2023-11-24T08:10:00</Timestamp>
  </MeanPublic>
  <MeanPublic>
    <Key>SN: 191246219 (SN: 191246219):191246219:DcMs.Amp[B]</Key>
    <Min>2.0280001237793</Min>
    <Max>4.38700026776125</Max>
    <Mean>3.27100019964601</Mean>
    <Base>1</Base>
    <Period>300</Period>
    <Timestamp>2023-11-24T08:10:00</Timestamp>
  </MeanPublic>
  <MeanPublic>
    <Key>Cluster Controller:165012367:GridMs.PhV.phsA</Key>
    <Min>272.91</Min>
    <Max>274.95</Max>
    <Mean>274.04</Mean>
    <Base>1</Base>
    <Period>300</Period>
    <Timestamp>2023-11-24T08:10:00</Timestamp>
  </MeanPublic>
  <MeanPublic>
    <Key>SN: 191240180 (SN: 191240180):191240180:GridMs.PhV.phsA</Key>
    <Min>272.91</Min>
    <Max>274.18</Max>
    <Mean>273.63</Mean>
    <Base>1</Base>
    <Period>300</Period>
    <Timestamp>2023-11-24T08:10:00</Timestamp>
  </MeanPublic>
  <MeanPublic>
    <Key>SN: 191240234 (SN: 191240234):191240234:GridMs.PhV.phsA</Key>
    <Min>273.38</Min>
    <Max>274.65</Max>
    <Mean>274.12</Mean>
    <Base>1</Base>
    <Period>300</Period>
    <Timestamp>2023-11-24T08:10:00</Timestamp>
  </MeanPublic>
  <MeanPublic>
    <Key>SN: 191246219 (SN: 191246219):191246219:GridMs.PhV.phsA</Key>
    <Min>273.65</Min>
    <Max>274.95</Max>
    <Mean>274.38</Mean>
    <Base>1</Base>
    <Period>300</Period>
    <Timestamp>2023-11-24T08:10:00</Timestamp>
  </MeanPublic>
  <MeanPublic>
    <Key>Cluster Controller:165012367:GridMs.PhV.phsB</Key>
    <Min>272.88</Min>
    <Max>274.82</Max>
    <Mean>273.94</Mean>
    <Base>1</Base>
    <Period>300</Period>
    <Timestamp>2023-11-24T08:10:00</Timestamp>
  </MeanPublic>
  <MeanPublic>
    <Key>Cluster Controller:165012367:GridMs.PhV.phsC</Key>
    <Min>272.07</Min>
    <Max>274.03</Max>
    <Mean>273.08</Mean>
    <Base>1</Base>
    <Period>300</Period>
    <Timestamp>2023-11-24T08:10:00</Timestamp>
  </MeanPublic>
  <MeanPublic>
    <Key>Cluster Controller:165012367:GridMs.A.phsA</Key>
    <Min>1.27800007800293</Min>
    <Max>5.04400030786135</Max>
    <Mean>2.67600016333009</Mean>
    <Base>1</Base>
    <Period>300</Period>
    <Timestamp>2023-11-24T08:10:00</Timestamp>
  </MeanPublic>
  <MeanPublic>
    <Key>SN: 191240180 (SN: 191240180):191240180:GridMs.PhV.phsB</Key>
    <Min>273.14</Min>
    <Max>274.52</Max>
    <Mean>273.92</Mean>
    <Base>1</Base>
    <Period>300</Period>
    <Timestamp>2023-11-24T08:10:00</Timestamp>
  </MeanPublic>
  <MeanPublic>
    <Key>SN: 191240180 (SN: 191240180):191240180:GridMs.PhV.phsC</Key>
    <Min>272.31</Min>
    <Max>273.46</Max>
    <Mean>272.99</Mean>
    <Base>1</Base>
    <Period>300</Period>
    <Timestamp>2023-11-24T08:10:00</Timestamp>
  </MeanPublic>
  <MeanPublic>
    <Key>SN: 191240180 (SN: 191240180):191240180:GridMs.A.phsA</Key>
    <Min>1.27800007800293</Min>
    <Max>2.82900017266847</Max>
    <Mean>2.11700012921143</Mean>
    <Base>1</Base>
    <Period>300</Period>
    <Timestamp>2023-11-24T08:10:00</Timestamp>
  </MeanPublic>
  <MeanPublic>
    <Key>SN: 191240234 (SN: 191240234):191240234:GridMs.PhV.phsB</Key>
    <Min>272.88</Min>
    <Max>274.2</Max>
    <Mean>273.67</Mean>
    <Base>1</Base>
    <Period>300</Period>
    <Timestamp>2023-11-24T08:10:00</Timestamp>
  </MeanPublic>
  <MeanPublic>
    <Key>SN: 191240234 (SN: 191240234):191240234:GridMs.PhV.phsC</Key>
    <Min>272.07</Min>
    <Max>273.19</Max>
    <Mean>272.75</Mean>
    <Base>1</Base>
    <Period>300</Period>
    <Timestamp>2023-11-24T08:10:00</Timestamp>
  </MeanPublic>
  <MeanPublic>
    <Key>SN: 191240234 (SN: 191240234):191240234:GridMs.A.phsA</Key>
    <Min>1.32300008074952</Min>
    <Max>2.06900012628175</Max>
    <Mean>1.87800011462403</Mean>
    <Base>1</Base>
    <Period>300</Period>
    <Timestamp>2023-11-24T08:10:00</Timestamp>
  </MeanPublic>
  <MeanPublic>
    <Key>SN: 191246219 (SN: 191246219):191246219:GridMs.PhV.phsB</Key>
    <Min>273.46</Min>
    <Max>274.82</Max>
    <Mean>274.25</Mean>
    <Base>1</Base>
    <Period>300</Period>
    <Timestamp>2023-11-24T08:10:00</Timestamp>
  </MeanPublic>
  <MeanPublic>
    <Key>SN: 191246219 (SN: 191246219):191246219:GridMs.PhV.phsC</Key>
    <Min>272.76</Min>
    <Max>274.03</Max>
    <Mean>273.5</Mean>
    <Base>1</Base>
    <Period>300</Period>
    <Timestamp>2023-11-24T08:10:00</Timestamp>
  </MeanPublic>
  <MeanPublic>
    <Key>SN: 191246219 (SN: 191246219):191246219:GridMs.A.phsA</Key>
    <Min>2.69300016436769</Min>
    <Max>5.04400030786135</Max>
    <Mean>4.03500024627687</Mean>
    <Base>1</Base>
    <Period>300</Period>
    <Timestamp>2023-11-24T08:10:00</Timestamp>
  </MeanPublic>
  <MeanPublic>
    <Key>Cluster Controller:165012367:GridMs.A.phsB</Key>
    <Min>1.25900007684327</Min>
    <Max>4.96000030273439</Max>
    <Mean>2.63800016101075</Mean>
    <Base>1</Base>
    <Period>300</Period>
    <Timestamp>2023-11-24T08:10:00</Timestamp>
  </MeanPublic>
  <MeanPublic>
    <Key>Cluster Controller:165012367:GridMs.A.phsC</Key>
    <Min>1.25200007641602</Min>
    <Max>5.0370003074341</Max>
    <Mean>2.6620001624756</Mean>
    <Base>1</Base>
    <Period>300</Period>
    <Timestamp>2023-11-24T08:10:00</Timestamp>
  </MeanPublic>
  <MeanPublic>
    <Key>SN: 191240180 (SN: 191240180):191240180:GridMs.A.phsB</Key>
    <Min>1.25900007684327</Min>
    <Max>2.80800017138673</Max>
    <Mean>2.09700012799073</Mean>
    <Base>1</Base>
    <Period>300</Period>
    <Timestamp>2023-11-24T08:10:00</Timestamp>
  </MeanPublic>
  <MeanPublic>
    <Key>SN: 191240180 (SN: 191240180):191240180:GridMs.A.phsC</Key>
    <Min>1.25200007641602</Min>
    <Max>2.81600017187501</Max>
    <Mean>2.0990001281128</Mean>
    <Base>1</Base>
    <Period>300</Period>
    <Timestamp>2023-11-24T08:10:00</Timestamp>
  </MeanPublic>
  <MeanPublic>
    <Key>SN: 191240234 (SN: 191240234):191240234:GridMs.A.phsB</Key>
    <Min>1.30300007952881</Min>
    <Max>2.04900012506104</Max>
    <Mean>1.85900011346436</Mean>
    <Base>1</Base>
    <Period>300</Period>
    <Timestamp>2023-11-24T08:10:00</Timestamp>
  </MeanPublic>
  <MeanPublic>
    <Key>SN: 191240234 (SN: 191240234):191240234:GridMs.A.phsC</Key>
    <Min>1.30500007965088</Min>
    <Max>2.05900012567139</Max>
    <Mean>1.86500011383057</Mean>
    <Base>1</Base>
    <Period>300</Period>
    <Timestamp>2023-11-24T08:10:00</Timestamp>
  </MeanPublic>
  <MeanPublic>
    <Key>SN: 191246219 (SN: 191246219):191246219:GridMs.A.phsB</Key>
    <Min>2.62000015991212</Min>
    <Max>4.96000030273439</Max>
    <Mean>3.95800024157716</Mean>
    <Base>1</Base>
    <Period>300</Period>
    <Timestamp>2023-11-24T08:10:00</Timestamp>
  </MeanPublic>
  <MeanPublic>
    <Key>SN: 191246219 (SN: 191246219):191246219:GridMs.A.phsC</Key>
    <Min>2.67500016326905</Min>
    <Max>5.0370003074341</Max>
    <Mean>4.02300024554445</Mean>
    <Base>1</Base>
    <Period>300</Period>
    <Timestamp>2023-11-24T08:10:00</Timestamp>
  </MeanPublic>
  <MeanPublic>
    <Key>Cluster Controller:165012367:DcMs.Watt[A]</Key>
    <Min>330</Min>
    <Max>1531</Max>
    <Mean>3000</Mean>
    <Base>1</Base>
    <Period>300</Period>
    <Timestamp>2023-11-24T08:10:00</Timestamp>
  </MeanPublic>
  <MeanPublic>
    <Key>Cluster Controller:165012367:DcMs.Watt[B]</Key>
    <Min>475</Min>
    <Max>2629</Max>
    <Mean>3542</Mean>
    <Base>1</Base>
    <Period>300</Period>
    <Timestamp>2023-11-24T08:10:00</Timestamp>
  </MeanPublic>
  <MeanPublic>
    <Key>SN: 191240180 (SN: 191240180):191240180:DcMs.Watt[A]</Key>
    <Min>509</Min>
    <Max>1174</Max>
    <Mean>873</Mean>
    <Base>1</Base>
    <Period>300</Period>
    <Timestamp>2023-11-24T08:10:00</Timestamp>
  </MeanPublic>
  <MeanPublic>
    <Key>SN: 191240180 (SN: 191240180):191240180:DcMs.Watt[B]</Key>
    <Min>500</Min>
    <Max>1142</Max>
    <Mean>842</Mean>
    <Base>1</Base>
    <Period>300</Period>
    <Timestamp>2023-11-24T08:10:00</Timestamp>
  </MeanPublic>
  <MeanPublic>
    <Key>SN: 191240234 (SN: 191240234):191240234:DcMs.Watt[A]</Key>
    <Min>330</Min>
    <Max>849</Max>
    <Mean>771</Mean>
    <Base>1</Base>
    <Period>300</Period>
    <Timestamp>2023-11-24T08:10:00</Timestamp>
  </MeanPublic>
  <MeanPublic>
    <Key>SN: 191240234 (SN: 191240234):191240234:DcMs.Watt[B]</Key>
    <Min>475</Min>
    <Max>831</Max>
    <Mean>747</Mean>
    <Base>1</Base>
    <Period>300</Period>
    <Timestamp>2023-11-24T08:10:00</Timestamp>
  </MeanPublic>
  <MeanPublic>
    <Key>SN: 191246219 (SN: 191246219):191246219:DcMs.Watt[A]</Key>
    <Min>961</Min>
    <Max>1531</Max>
    <Mean>1356</Mean>
    <Base>1</Base>
    <Period>300</Period>
    <Timestamp>2023-11-24T08:10:00</Timestamp>
  </MeanPublic>
  <MeanPublic>
    <Key>SN: 191246219 (SN: 191246219):191246219:DcMs.Watt[B]</Key>
    <Min>1208</Min>
    <Max>2629</Max>
    <Mean>1953</Mean>
    <Base>1</Base>
    <Period>300</Period>
    <Timestamp>2023-11-24T08:10:00</Timestamp>
  </MeanPublic>
  <CurrentPublic>
    <Key>Cluster Controller:165012367:Operation.Health</Key>
    <Mean>Ok</Mean>
    <Base>1</Base>
    <Period>300</Period>
    <Timestamp>2023-11-24T08:10:00</Timestamp>
  </CurrentPublic>
  <CurrentPublic>
    <Key>SN: 191240180 (SN: 191240180):191240180:Operation.Health</Key>
    <Mean>Ok</Mean>
    <Base>1</Base>
    <Period>300</Period>
    <Timestamp>2023-11-24T08:10:00</Timestamp>
  </CurrentPublic>
  <CurrentPublic>
    <Key>SN: 191240180 (SN: 191240180):191240180:Operation.Evt.Prio</Key>
    <Mean>NonePrio</Mean>
    <Base>1</Base>
    <Period>300</Period>
    <Timestamp>2023-11-24T08:10:00</Timestamp>
  </CurrentPublic>
  <CurrentPublic>
    <Key>SN: 191240180 (SN: 191240180):191240180:Operation.Evt.Msg</Key>
    <Mean>None</Mean>
    <Base>1</Base>
    <Period>300</Period>
    <Timestamp>2023-11-24T08:10:00</Timestamp>
  </CurrentPublic>
  <CurrentPublic>
    <Key>SN: 191240234 (SN: 191240234):191240234:Operation.Health</Key>
    <Mean>Ok</Mean>
    <Base>1</Base>
    <Period>300</Period>
    <Timestamp>2023-11-24T08:10:00</Timestamp>
  </CurrentPublic>
  <CurrentPublic>
    <Key>SN: 191240234 (SN: 191240234):191240234:Operation.Evt.Prio</Key>
    <Mean>NonePrio</Mean>
    <Base>1</Base>
    <Period>300</Period>
    <Timestamp>2023-11-24T08:10:00</Timestamp>
  </CurrentPublic>
  <CurrentPublic>
    <Key>SN: 191240234 (SN: 191240234):191240234:Operation.Evt.Msg</Key>
    <Mean>None</Mean>
    <Base>1</Base>
    <Period>300</Period>
    <Timestamp>2023-11-24T08:10:00</Timestamp>
  </CurrentPublic>
  <CurrentPublic>
    <Key>SN: 191246219 (SN: 191246219):191246219:Operation.Health</Key>
    <Mean>Ok</Mean>
    <Base>1</Base>
    <Period>300</Period>
    <Timestamp>2023-11-24T08:10:00</Timestamp>
  </CurrentPublic>
  <CurrentPublic>
    <Key>SN: 191246219 (SN: 191246219):191246219:Operation.Evt.Prio</Key>
    <Mean>NonePrio</Mean>
    <Base>1</Base>
    <Period>300</Period>
    <Timestamp>2023-11-24T08:10:00</Timestamp>
  </CurrentPublic>
  <CurrentPublic>
    <Key>SN: 191246219 (SN: 191246219):191246219:Operation.Evt.Msg</Key>
    <Mean>None</Mean>
    <Base>1</Base>
    <Period>300</Period>
    <Timestamp>2023-11-24T08:10:00</Timestamp>
  </CurrentPublic>
  <CurrentPublic>
    <Key>SN: 191240180 (SN: 191240180):191240180:Operation.Evt.Dsc</Key>
    <Mean>None</Mean>
    <Base>1</Base>
    <Period>300</Period>
    <Timestamp>2023-11-24T08:10:00</Timestamp>
  </CurrentPublic>
  <CurrentPublic>
    <Key>SN: 191240234 (SN: 191240234):191240234:Operation.Evt.Dsc</Key>
    <Mean>None</Mean>
    <Base>1</Base>
    <Period>300</Period>
    <Timestamp>2023-11-24T08:10:00</Timestamp>
  </CurrentPublic>
  <CurrentPublic>
    <Key>SN: 191246219 (SN: 191246219):191246219:Operation.Evt.Dsc</Key>
    <Mean>None</Mean>
    <Base>1</Base>
    <Period>300</Period>
    <Timestamp>2023-11-24T08:10:00</Timestamp>
  </CurrentPublic>
  <CurrentPublic>
    <Key>Cluster Controller:165012367:InOut.AnInA2</Key>
    <Min>0</Min>
    <Max>0</Max>
    <Mean>0</Mean>
    <Base>1</Base>
    <Period>300</Period>
    <Timestamp>2023-11-24T08:10:00</Timestamp>
  </CurrentPublic>
  <CurrentPublic>
    <Key>Cluster Controller:165012367:InOut.AnInA3</Key>
    <Min>0</Min>
    <Max>0</Max>
    <Mean>0</Mean>
    <Base>1</Base>
    <Period>300</Period>
    <Timestamp>2023-11-24T08:10:00</Timestamp>
  </CurrentPublic>
  <CurrentPublic>
    <Key>Cluster Controller:165012367:InOut.AnInVol4</Key>
    <Min>2.07</Min>
    <Max>2.07</Max>
    <Mean>2.07</Mean>
    <Base>1</Base>
    <Period>300</Period>
    <Timestamp>2023-11-24T08:10:00</Timestamp>
  </CurrentPublic>
</ClusterController>