<?xml version="1.0" encoding="utf-8"?>
<ClusterController>
  <Info>
    <Created>2023-11-24T08:40:00</Created>
    <Culture>en</Culture>
    <UtcOffset>-480</UtcOffset>
    <DST>False</DST>
    <FW-Version>1.05.01.4</FW-Version>
  </Info>
  <CurrentPublic>
    <Key>Cluster Controller:165012367:Metering.TotWhOut</Key>
    <Mean>357187.4</Mean>
    <Base>1</Base>
    <Period>300</Period>
    <Timestamp>2023-11-24T08:40:00</Timestamp>
  </CurrentPublic>
  <CurrentPublic>
    <Key>Cluster Controller:165012367:Operation.GriSwCnt</Key>
    <Mean>5234</Mean>
    <Base>1</Base>
    <Period>300</Period>
    <Timestamp>2023-11-24T08:40:00</Timestamp>
  </CurrentPublic>
  <CurrentPublic>
    <Key>Cluster Controller:165012367:Metering.TotOpTms</Key>
    <Mean>58115.13</Mean>
    <Base>1</Base>
    <Period>300</Period>
    <Timestamp>2023-11-24T08:40:00</Timestamp>
  </CurrentPublic>
  <CurrentPublic>
    <Key>SN: 191240180 (SN: 191240180):191240180:Metering.TotWhOut</Key>
    <Mean>118940.7</Mean>
    <Base>1</Base>
    <Period>300</Period>
    <Timestamp>2023-11-24T08:40:00</Timestamp>
  </CurrentPublic>
  <CurrentPublic>
    <Key>SN: 191240180 (SN: 191240180):191240180:Operation.GriSwCnt</Key>
    <Mean>2515</Mean>
    <Base>1</Base>
    <Period>300</Period>
    <Timestamp>2023-11-24T08:40:00</Timestamp>
  </CurrentPublic>
  <CurrentPublic>
    <Key>SN: 191240180 (SN: 191240180):191240180:Metering.TotOpTms</Key>
    <Mean>27254.93</Mean>
    <Base>1</Base>
    <Period>300</Period>
    <Timestamp>2023-11-24T08:40:00</Timestamp>
  </CurrentPublic>
  <CurrentPublic>
    <Key>SN: 191240234 (SN: 191240234):191240234:Metering.TotWhOut</Key>
    <Mean>203622.4</Mean>
    <Base>1</Base>
    <Period>300</Period>
    <Timestamp>2023-11-24T08:40:00</Timestamp>
  </CurrentPublic>
  <CurrentPublic>
    <Key>SN: 191240234 (SN: 191240234):191240234:Operation.GriSwCnt</Key>
    <Mean>2451</Mean>
    <Base>1</Base>
    <Period>300</Period>
    <Timestamp>2023-11-24T08:40:00</Timestamp>
  </CurrentPublic>
  <CurrentPublic>
    <Key>SN: 191240234 (SN: 191240234):191240234:Metering.TotOpTms</Key>
    <Mean>27507.69</Mean>
    <Base>1</Base>
    <Period>300</Period>
    <Timestamp>2023-11-24T08:40:00</Timestamp>
  </CurrentPublic>
  <CurrentPublic>
    <Key>SN: 191246219 (SN: 191246219):191246219:Metering.TotWhOut</Key>
    <Mean>34624.43</Mean>
    <Base>1</Base>
    <Period>300</Period>
    <Timestamp>2023-11-24T08:40:00</Timestamp>
  </CurrentPublic>
  <CurrentPublic>
    <Key>SN: 191246219 (SN: 191246219):191246219:Operation.GriSwCnt</Key>
    <Mean>268</Mean>
    <Base>1</Base>
    <Period>300</Period>
    <Timestamp>2023-11-24T08:40:00</Timestamp>
  </CurrentPublic>
  <CurrentPublic>
    <Key>SN: 191246219 (SN: 191246219):191246219:Metering.TotOpTms</Key>
    <Mean>3352.522</Mean>
    <Base>1</Base>
    <Period>300</Period>
    <Timestamp>2023-11-24T08:40:00</Timestamp>
  </CurrentPublic>
  <CurrentPublic>
    <Key>Cluster Controller:165012367:Metering.TotFeedTms</Key>
    <Mean>56845.21</Mean>
    <Base>1</Base>
    <Period>300</Period>
    <Timestamp>2023-11-24T08:40:00</Timestamp>
  </CurrentPublic>
  <CurrentPublic>
    <Key>SN: 191240180 (SN: 191240180):191240180:Metering.TotFeedTms</Key>
    <Mean>26496.6</Mean>
    <Base>1</Base>
    <Period>300</Period>
    <Timestamp>2023-11-24T08:40:00</Timestamp>
  </CurrentPublic>
  <CurrentPublic>
    <Key>SN: 191240180 (SN: 191240180):191240180:Metering.GridMs.TotWhOut</Key>
    <Mean>1.844674E+16</Mean>
    <Base>1</Base>
    <Period>300</Period>
    <Timestamp>2023-11-24T08:40:00</Timestamp>
  </CurrentPublic>
  <CurrentPublic>
    <Key>SN: 191240234 (SN: 191240234):191240234:Metering.TotFeedTms</Key>
    <Mean>27057.66</Mean>
    <Base>1</Base>
    <Period>300</Period>
    <Timestamp>2023-11-24T08:40:00</Timestamp>
  </CurrentPublic>
  <CurrentPublic>
    <Key>SN: 191240234 (SN: 191240234):191240234:Metering.GridMs.TotWhOut</Key>
    <Mean>1.844674E+16</Mean>
    <Base>1</Base>
    <Period>300</Period>
    <Timestamp>2023-11-24T08:40:00</Timestamp>
  </CurrentPublic>
  <CurrentPublic>
    <Key>SN: 191246219 (SN: 191246219):191246219:Metering.TotFeedTms</Key>
    <Mean>3290.958</Mean>
    <Base>1</Base>
    <Period>300</Period>
    <Timestamp>2023-11-24T08:40:00</Timestamp>
  </CurrentPublic>
  <CurrentPublic>
    <Key>SN: 191246219 (SN: 191246219):191246219:Metering.GridMs.TotWhOut</Key>
    <Mean>1.844674E+16</Mean>
    <Base>1</Base>
    <Period>300</Period>
    <Timestamp>2023-11-24T08:40:00</Timestamp>
  </CurrentPublic>
  <MeanPublic>
    <Key>Cluster Controller:165012367:GridMs.TotW</Key>
    <Min>1896</Min>
    <Max>9026</Max>
    <Mean>13497</Mean>
    <Base>1</Base>
    <Period>300</Period>
    <Timestamp>2023-11-24T08:40:00</Timestamp>
  </MeanPublic>
  <MeanPublic>
    <Key>Cluster Controller:165012367:GridMs.Hz</Key>
    <Min>59.97</Min>
    <Max>60.01</Max>
    <Mean>60</Mean>
    <Base>1</Base>
    <Period>300</Period>
    <Timestamp>2023-11-24T08:40:00</Timestamp>
  </MeanPublic>
  <MeanPublic>
    <Key>SN: 191240180 (SN: 191240180):191240180:GridMs.TotW</Key>
    <Min>1896</Min>
    <Max>3680</Max>
    <Mean>3128</Mean>
    <Base>1</Base>
    <Period>300</Period>
    <Timestamp>2023-11-24T08:40:00</Timestamp>
  </MeanPublic>
  <MeanPublic>
    <Key>SN: 191240180 (SN: 191240180):191240180:GridMs.Hz</Key>
    <Min>59.97</Min>
    <Max>60.01</Max>
    <Mean>60</Mean>
    <Base>1</Base>
    <Period>300</Period>
    <Timestamp>2023-11-24T08:40:00</Timestamp>
  </MeanPublic>
  <MeanPublic>
    <Key>SN: 191240234 (SN: 191240234):191240234:GridMs.TotW</Key>
    <Min>1924</Min>
    <Max>3695</Max>
    <Mean>2794</Mean>
    <Base>1</Base>
    <Period>300</Period>
    <Timestamp>2023-11-24T08:40:00</Timestamp>
  </MeanPublic>
  <MeanPublic>
    <Key>SN: 191240234 (SN: 191240234):191240234:GridMs.Hz</Key>
    <Min>59.98</Min>
    <Max>60.01</Max>
    <Mean>60</Mean>
    <Base>1</Base>
    <Period>300</Period>
    <Timestamp>2023-11-24T08:40:00</Timestamp>
  </MeanPublic>
  <MeanPublic>
    <Key>SN: 191246219 (SN: 191246219):191246219:GridMs.TotW</Key>
    <Min>4630</Min>
    <Max>9026</Max>
    <Mean>7575</Mean>
    <Base>1</Base>
    <Period>300</Period>
    <Timestamp>2023-11-24T08:40:00</Timestamp>
  </MeanPublic>
  <MeanPublic>
    <Key>SN: 191246219 (SN: 191246219):191246219:GridMs.Hz</Key>
    <Min>59.98</Min>
    <Max>60.01</Max>
    <Mean>60</Mean>
    <Base>1</Base>
    <Period>300</Period>
    <Timestamp>2023-11-24T08:40:00</Timestamp>
  </MeanPublic>
  <CurrentPublic>
    <Key>Cluster Controller:165012367:Isolation.FltA</Key>
    <Min>17</Min>
    <Max>18</Max>
    <Mean>17</Mean>
    <Base>1</Base>
    <Period>300</Period>
    <Timestamp>2023-11-24T08:40:00</Timestamp>
  </CurrentPublic>
  <CurrentPublic>
    <Key>SN: 191240180 (SN: 191240180):191240180:Isolation.FltA</Key>
    <Min>17</Min>
    <Max>17</Max>
    <Mean>17</Mean>
    <Base>1</Base>
    <Period>300</Period>
    <Timestamp>2023-11-24T08:40:00</Timestamp>
  </CurrentPublic>
  <CurrentPublic>
    <Key>SN: 191240234 (SN: 191240234):191240234:Isolation.FltA</Key>
    <Min>18</Min>
    <Max>18</Max>
    <Mean>18</Mean>
    <Base>1</Base>
    <Period>300</Period>
    <Timestamp>2023-11-24T08:40:00</Timestamp>
  </CurrentPublic>
  <CurrentPublic>
    <Key>SN: 191246219 (SN: 191246219):191246219:Isolation.FltA</Key>
    <Min>17</Min>
    <Max>17</Max>
    <Mean>17</Mean>
    <Base>1</Base>
    <Period>300</Period>
    <Timestamp>2023-11-24T08:40:00</Timestamp>
  </CurrentPublic>
  <CurrentPublic>
    <Key>Cluster Controller:165012367:Isolation.LeakRis</Key>
    <Min>626.809</Min>
    <Max>2565.516</Max>
    <Mean>1377.233</Mean>
    <Base>1</Base>
    <Period>300</Period>
    <Timestamp>2023-11-24T08:40:00</Timestamp>
  </CurrentPublic>
  <CurrentPublic>
    <Key>SN: 191240180 (SN: 191240180):191240180:Isolation.LeakRis</Key>
    <Min>2565.516</Min>
    <Max>2565.516</Max>
    <Mean>2565.516</Mean>
    <Base>1</Base>
    <Period>300</Period>
    <Timestamp>2023-11-24T08:40:00</Timestamp>
  </CurrentPublic>
  <CurrentPublic>
    <Key>SN: 191240234 (SN: 191240234):191240234:Isolation.LeakRis</Key>
    <Min>939.375</Min>
    <Max>939.375</Max>
    <Mean>939.375</Mean>
    <Base>1</Base>
    <Period>300</Period>
    <Timestamp>2023-11-24T08:40:00</Timestamp>
  </CurrentPublic>
  <CurrentPublic>
    <Key>SN: 191246219 (SN: 191246219):191246219:Isolation.LeakRis</Key>
    <Min>626.809</Min>
    <Max>626.809</Max>
    <Mean>626.809</Mean>
    <Base>1</Base>
    <Period>300</Period>
    <Timestamp>2023-11-24T08:40:00</Timestamp>
  </CurrentPublic>
  <MeanPublic>
    <Key>Cluster Controller:165012367:DcMs.Vol[A]</Key>
    <Min>325.17</Min>
    <Max>657.12</Max>
    <Mean>595.46</Mean>
    <Base>1</Base>
    <Period>300</Period>
    <Timestamp>2023-11-24T08:40:00</Timestamp>
  </MeanPublic>
  <MeanPublic>
    <Key>Cluster Controller:165012367:DcMs.Vol[B]</Key>
    <Min>257.34</Min>
    <Max>624.43</Max>
    <Mean>503.51</Mean>
    <Base>1</Base>
    <Period>300</Period>
    <Timestamp>2023-11-24T08:40:00</Timestamp>
  </MeanPublic>
  <MeanPublic>
    <Key>SN: 191240180 (SN: 191240180):191240180:DcMs.Vol[A]</Key>
    <Min>386.99</Min>
    <Max>538.72</Max>
    <Mean>530.65</Mean>
    <Base>1</Base>
    <Period>300</Period>
    <Timestamp>2023-11-24T08:40:00</Timestamp>
  </MeanPublic>
  <MeanPublic>
    <Key>SN: 191240180 (SN: 191240180):191240180:DcMs.Vol[B]</Key>
    <Min>272.39</Min>
    <Max>536.05</Max>
    <Mean>500.16</Mean>
    <Base>1</Base>
    <Period>300</Period>
    <Timestamp>2023-11-24T08:40:00</Timestamp>
  </MeanPublic>
  <MeanPublic>
    <Key>SN: 191240234 (SN: 191240234):191240234:DcMs.Vol[A]</Key>
    <Min>468.86</Min>
    <Max>657.12</Max>
    <Mean>646.93</Mean>
    <Base>1</Base>
    <Period>300</Period>
    <Timestamp>2023-11-24T08:40:00</Timestamp>
  </MeanPublic>
  <MeanPublic>
    <Key>SN: 191240234 (SN: 191240234):191240234:DcMs.Vol[B]</Key>
    <Min>316.9</Min>
    <Max>576.23</Max>
    <Mean>410.84</Mean>
    <Base>1</Base>
    <Period>300</Period>
    <Timestamp>2023-11-24T08:40:00</Timestamp>
  </MeanPublic>
  <MeanPublic>
    <Key>SN: 191246219 (SN: 191246219):191246219:DcMs.Vol[A]</Key>
    <Min>325.17</Min>
    <Max>646.44</Max>
    <Mean>608.81</Mean>
    <Base>1</Base>
    <Period>300</Period>
    <Timestamp>2023-11-24T08:40:00</Timestamp>
  </MeanPublic>
  <MeanPublic>
    <Key>SN: 191246219 (SN: 191246219):191246219:DcMs.Vol[B]</Key>
    <Min>257.34</Min>
    <Max>624.43</Max>
    <Mean>599.54</Mean>
    <Base>1</Base>
    <Period>300</Period>
    <Timestamp>2023-11-24T08:40:00</Timestamp>
  </MeanPublic>
  <MeanPublic>
    <Key>Cluster Controller:165012367:DcMs.Amp[A]</Key>
    <Min>1.52400009301758</Min>
    <Max>7.90500048248294</Max>
    <Mean>3.81900023309328</Mean>
    <Base>1</Base>
    <Period>300</Period>
    <Timestamp>2023-11-24T08:40:00</Timestamp>
  </MeanPublic>
  <MeanPublic>
    <Key>Cluster Controller:165012367:DcMs.Amp[B]</Key>
    <Min>1.75100010687257</Min>
    <Max>7.96800048632815</Max>
    <Mean>4.38800026782228</Mean>
    <Base>1</Base>
    <Period>300</Period>
    <Timestamp>2023-11-24T08:40:00</Timestamp>
  </MeanPublic>
  <MeanPublic>
    <Key>SN: 191240180 (SN: 191240180):191240180:DcMs.Amp[A]</Key>
    <Min>1.89500011566163</Min>
    <Max>3.78100023077394</Max>
    <Mean>3.1740001937256</Mean>
    <Base>1</Base>
    <Period>300</Period>
    <Timestamp>2023-11-24T08:40:00</Timestamp>
  </MeanPublic>
  <MeanPublic>
    <Key>SN: 191240180 (SN: 191240180):191240180:DcMs.Amp[B]</Key>
    <Min>1.75100010687257</Min>
    <Max>3.45100021063234</Max>
    <Mean>2.96900018121339</Mean>
    <Base>1</Base>
    <Period>300</Period>
    <Timestamp>2023-11-24T08:40:00</Timestamp>
  </MeanPublic>
  <MeanPublic>
    <Key>SN: 191240234 (SN: 191240234):191240234:DcMs.Amp[A]</Key>
    <Min>1.52400009301758</Min>
    <Max>2.53800015490724</Max>
    <Mean>1.89200011547852</Mean>
    <Base>1</Base>
    <Period>300</Period>
    <Timestamp>2023-11-24T08:40:00</Timestamp>
  </MeanPublic>
  <MeanPublic>
    <Key>SN: 191240234 (SN: 191240234):191240234:DcMs.Amp[B]</Key>
    <Min>2.56700015667726</Min>
    <Max>4.8010002930298</Max>
    <Mean>3.86900023614503</Mean>
    <Base>1</Base>
    <Period>300</Period>
    <Timestamp>2023-11-24T08:40:00</Timestamp>
  </MeanPublic>
  <MeanPublic>
    <Key>SN: 191246219 (SN: 191246219):191246219:DcMs.Amp[A]</Key>
    <Min>3.85700023541261</Min>
    <Max>7.90500048248294</Max>
    <Mean>6.39300039019778</Mean>
    <Base>1</Base>
    <Period>300</Period>
    <Timestamp>2023-11-24T08:40:00</Timestamp>
  </MeanPublic>
  <MeanPublic>
    <Key>SN: 191246219 (SN: 191246219):191246219:DcMs.Amp[B]</Key>
    <Min>3.76100022955324</Min>
    <Max>7.96800048632815</Max>
    <Mean>6.32700038616946</Mean>
    <Base>1</Base>
    <Period>300</Period>
    <Timestamp>2023-11-24T08:40:00</Timestamp>
  </MeanPublic>
  <MeanPublic>
    <Key>Cluster Controller:165012367:GridMs.PhV.phsA</Key>
    <Min>273.35</Min>
    <Max>275.91</Max>
    <Mean>274.95</Mean>
    <Base>1</Base>
    <Period>300</Period>
    <Timestamp>2023-11-24T08:40:00</Timestamp>
  </MeanPublic>
  <MeanPublic>
    <Key>SN: 191240180 (SN: 191240180):191240180:GridMs.PhV.phsA</Key>
    <Min>273.35</Min>
    <Max>275.14</Max>
    <Mean>274.53</Mean>
    <Base>1</Base>
    <Period>300</Period>
    <Timestamp>2023-11-24T08:40:00</Timestamp>
  </MeanPublic>
  <MeanPublic>
    <Key>SN: 191240234 (SN: 191240234):191240234:GridMs.PhV.phsA</Key>
    <Min>273.63</Min>
    <Max>275.64</Max>
    <Mean>275.03</Mean>
    <Base>1</Base>
    <Period>300</Period>
    <Timestamp>2023-11-24T08:40:00</Timestamp>
  </MeanPublic>
  <MeanPublic>
    <Key>SN: 191246219 (SN: 191246219):191246219:GridMs.PhV.phsA</Key>
    <Min>274.08</Min>
    <Max>275.91</Max>
    <Mean>275.31</Mean>
    <Base>1</Base>
    <Period>300</Period>
    <Timestamp>2023-11-24T08:40:00</Timestamp>
  </MeanPublic>
  <MeanPublic>
    <Key>Cluster Controller:165012367:GridMs.PhV.phsB</Key>
    <Min>273.4</Min>
    <Max>276.18</Max>
    <Mean>275.14</Mean>
    <Base>1</Base>
    <Period>300</Period>
    <Timestamp>2023-11-24T08:40:00</Timestamp>
  </MeanPublic>
  <MeanPublic>
    <Key>Cluster Controller:165012367:GridMs.PhV.phsC</Key>
    <Min>272.14</Min>
    <Max>274.87</Max>
    <Mean>273.73</Mean>
    <Base>1</Base>
    <Period>300</Period>
    <Timestamp>2023-11-24T08:40:00</Timestamp>
  </MeanPublic>
  <MeanPublic>
    <Key>Cluster Controller:165012367:GridMs.A.phsA</Key>
    <Min>2.32900014215089</Min>
    <Max>10.9810006702271</Max>
    <Mean>5.47900033441164</Mean>
    <Base>1</Base>
    <Period>300</Period>
    <Timestamp>2023-11-24T08:40:00</Timestamp>
  </MeanPublic>
  <MeanPublic>
    <Key>SN: 191240180 (SN: 191240180):191240180:GridMs.PhV.phsB</Key>
    <Min>274.08</Min>
    <Max>275.69</Max>
    <Mean>275.07</Mean>
    <Base>1</Base>
    <Period>300</Period>
    <Timestamp>2023-11-24T08:40:00</Timestamp>
  </MeanPublic>
  <MeanPublic>
    <Key>SN: 191240180 (SN: 191240180):191240180:GridMs.PhV.phsC</Key>
    <Min>272.62</Min>
    <Max>274.28</Max>
    <Mean>273.63</Mean>
    <Base>1</Base>
    <Period>300</Period>
    <Timestamp>2023-11-24T08:40:00</Timestamp>
  </MeanPublic>
  <MeanPublic>
    <Key>SN: 191240180 (SN: 191240180):191240180:GridMs.A.phsA</Key>
    <Min>2.32900014215089</Min>
    <Max>4.48400027368166</Max>
    <Mean>3.81700023297121</Mean>
    <Base>1</Base>
    <Period>300</Period>
    <Timestamp>2023-11-24T08:40:00</Timestamp>
  </MeanPublic>
  <MeanPublic>
    <Key>SN: 191240234 (SN: 191240234):191240234:GridMs.PhV.phsB</Key>
    <Min>273.4</Min>
    <Max>275.47</Max>
    <Mean>274.82</Mean>
    <Base>1</Base>
    <Period>300</Period>
    <Timestamp>2023-11-24T08:40:00</Timestamp>
  </MeanPublic>
  <MeanPublic>
    <Key>SN: 191240234 (SN: 191240234):191240234:GridMs.PhV.phsC</Key>
    <Min>272.14</Min>
    <Max>274.07</Max>
    <Mean>273.39</Mean>
    <Base>1</Base>
    <Period>300</Period>
    <Timestamp>2023-11-24T08:40:00</Timestamp>
  </MeanPublic>
  <MeanPublic>
    <Key>SN: 191240234 (SN: 191240234):191240234:GridMs.A.phsA</Key>
    <Min>2.36000014404298</Min>
    <Max>4.49700027447511</Max>
    <Mean>3.40800020800783</Mean>
    <Base>1</Base>
    <Period>300</Period>
    <Timestamp>2023-11-24T08:40:00</Timestamp>
  </MeanPublic>
  <MeanPublic>
    <Key>SN: 191246219 (SN: 191246219):191246219:GridMs.PhV.phsB</Key>
    <Min>274.49</Min>
    <Max>276.18</Max>
    <Mean>275.54</Mean>
    <Base>1</Base>
    <Period>300</Period>
    <Timestamp>2023-11-24T08:40:00</Timestamp>
  </MeanPublic>
  <MeanPublic>
    <Key>SN: 191246219 (SN: 191246219):191246219:GridMs.PhV.phsC</Key>
    <Min>273.16</Min>
    <Max>274.87</Max>
    <Mean>274.18</Mean>
    <Base>1</Base>
    <Period>300</Period>
    <Timestamp>2023-11-24T08:40:00</Timestamp>
  </MeanPublic>
  <MeanPublic>
    <Key>SN: 191246219 (SN: 191246219):191246219:GridMs.A.phsA</Key>
    <Min>5.65900034539797</Min>
    <Max>10.9810006702271</Max>
    <Mean>9.21300056231693</Mean>
    <Base>1</Base>
    <Period>300</Period>
    <Timestamp>2023-11-24T08:40:00</Timestamp>
  </MeanPublic>
  <MeanPublic>
    <Key>Cluster Controller:165012367:GridMs.A.phsB</Key>
    <Min>2.30300014056397</Min>
    <Max>10.8710006635132</Max>
    <Mean>5.42400033105471</Mean>
    <Base>1</Base>
    <Period>300</Period>
    <Timestamp>2023-11-24T08:40:00</Timestamp>
  </MeanPublic>
  <MeanPublic>
    <Key>Cluster Controller:165012367:GridMs.A.phsC</Key>
    <Min>2.30700014080811</Min>
    <Max>10.9970006712037</Max>
    <Mean>5.47400033410647</Mean>
    <Base>1</Base>
    <Period>300</Period>
    <Timestamp>2023-11-24T08:40:00</Timestamp>
  </MeanPublic>
  <MeanPublic>
    <Key>SN: 191240180 (SN: 191240180):191240180:GridMs.A.phsB</Key>
    <Min>2.30300014056397</Min>
    <Max>4.44900027154543</Max>
    <Mean>3.78400023095705</Mean>
    <Base>1</Base>
    <Period>300</Period>
    <Timestamp>2023-11-24T08:40:00</Timestamp>
  </MeanPublic>
  <MeanPublic>
    <Key>SN: 191240180 (SN: 191240180):191240180:GridMs.A.phsC</Key>
    <Min>2.30700014080811</Min>
    <Max>4.4710002728882</Max>
    <Mean>3.80100023199464</Mean>
    <Base>1</Base>
    <Period>300</Period>
    <Timestamp>2023-11-24T08:40:00</Timestamp>
  </MeanPublic>
  <MeanPublic>
    <Key>SN: 191240234 (SN: 191240234):191240234:GridMs.A.phsB</Key>
    <Min>2.33200014233399</Min>
    <Max>4.46400027246095</Max>
    <Mean>3.37900020623781</Mean>
    <Base>1</Base>
    <Period>300</Period>
    <Timestamp>2023-11-24T08:40:00</Timestamp>
  </MeanPublic>
  <MeanPublic>
    <Key>SN: 191240234 (SN: 191240234):191240234:GridMs.A.phsC</Key>
    <Min>2.34900014337159</Min>
    <Max>4.4910002741089</Max>
    <Mean>3.39900020745851</Mean>
    <Base>1</Base>
    <Period>300</Period>
    <Timestamp>2023-11-24T08:40:00</Timestamp>
  </MeanPublic>
  <MeanPublic>
    <Key>SN: 191246219 (SN: 191246219):191246219:GridMs.A.phsB</Key>
    <Min>5.57300034014895</Min>
    <Max>10.8710006635132</Max>
    <Mean>9.10900055596927</Mean>
    <Base>1</Base>
    <Period>300</Period>
    <Timestamp>2023-11-24T08:40:00</Timestamp>
  </MeanPublic>
  <MeanPublic>
    <Key>SN: 191246219 (SN: 191246219):191246219:GridMs.A.phsC</Key>
    <Min>5.65800034533694</Min>
    <Max>10.9970006712037</Max>
    <Mean>9.22200056286625</Mean>
    <Base>1</Base>
    <Period>300</Period>
    <Timestamp>2023-11-24T08:40:00</Timestamp>
  </MeanPublic>
  <MeanPublic>
    <Key>Cluster Controller:165012367:DcMs.Watt[A]</Key>
    <Min>991</Min>
    <Max>4661</Max>
    <Mean>6796</Mean>
    <Base>1</Base>
    <Period>300</Period>
    <Timestamp>2023-11-24T08:40:00</Timestamp>
  </MeanPublic>
  <MeanPublic>
    <Key>Cluster Controller:165012367:DcMs.Watt[B]</Key>
    <Min>866</Min>
    <Max>4523</Max>
    <Mean>6873</Mean>
    <Base>1</Base>
    <Period>300</Period>
    <Timestamp>2023-11-24T08:40:00</Timestamp>
  </MeanPublic>
  <MeanPublic>
    <Key>SN: 191240180 (SN: 191240180):191240180:DcMs.Watt[A]</Key>
    <Min>1004</Min>
    <Max>2011</Max>
    <Mean>1683</Mean>
    <Base>1</Base>
    <Period>300</Period>
    <Timestamp>2023-11-24T08:40:00</Timestamp>
  </MeanPublic>
  <MeanPublic>
    <Key>SN: 191240180 (SN: 191240180):191240180:DcMs.Watt[B]</Key>
    <Min>866</Min>
    <Max>1711</Max>
    <Mean>1481</Mean>
    <Base>1</Base>
    <Period>300</Period>
    <Timestamp>2023-11-24T08:40:00</Timestamp>
  </MeanPublic>
  <MeanPublic>
    <Key>SN: 191240234 (SN: 191240234):191240234:DcMs.Watt[A]</Key>
    <Min>991</Min>
    <Max>1529</Max>
    <Mean>1222</Mean>
    <Base>1</Base>
    <Period>300</Period>
    <Timestamp>2023-11-24T08:40:00</Timestamp>
  </MeanPublic>
  <MeanPublic>
    <Key>SN: 191240234 (SN: 191240234):191240234:DcMs.Watt[B]</Key>
    <Min>906</Min>
    <Max>2204</Max>
    <Mean>1602</Mean>
    <Base>1</Base>
    <Period>300</Period>
    <Timestamp>2023-11-24T08:40:00</Timestamp>
  </MeanPublic>
  <MeanPublic>
    <Key>SN: 191246219 (SN: 191246219):191246219:DcMs.Watt[A]</Key>
    <Min>2332</Min>
    <Max>4661</Max>
    <Mean>3891</Mean>
    <Base>1</Base>
    <Period>300</Period>
    <Timestamp>2023-11-24T08:40:00</Timestamp>
  </MeanPublic>
  <MeanPublic>
    <Key>SN: 191246219 (SN: 191246219):191246219:DcMs.Watt[B]</Key>
    <Min>2043</Min>
    <Max>4523</Max>
    <Mean>3790</Mean>
    <Base>1</Base>
    <Period>300</Period>
    <Timestamp>2023-11-24T08:40:00</Timestamp>
  </MeanPublic>
  <CurrentPublic>
    <Key>Cluster Controller:165012367:Operation.Health</Key>
    <Mean>Ok</Mean>
    <Base>1</Base>
    <Period>300</Period>
    <Timestamp>2023-11-24T08:40:00</Timestamp>
  </CurrentPublic>
  <CurrentPublic>
    <Key>SN: 191240180 (SN: 191240180):191240180:Operation.Health</Key>
    <Mean>Ok</Mean>
    <Base>1</Base>
    <Period>300</Period>
    <Timestamp>2023-11-24T08:40:00</Timestamp>
  </CurrentPublic>
  <CurrentPublic>
    <Key>SN: 191240180 (SN: 191240180):191240180:Operation.Evt.Prio</Key>
    <Mean>NonePrio</Mean>
    <Base>1</Base>
    <Period>300</Period>
    <Timestamp>2023-11-24T08:40:00</Timestamp>
  </CurrentPublic>
  <CurrentPublic>
    <Key>SN: 191240180 (SN: 191240180):191240180:Operation.Evt.Msg</Key>
    <Mean>None</Mean>
    <Base>1</Base>
    <Period>300</Period>
    <Timestamp>2023-11-24T08:40:00</Timestamp>
  </CurrentPublic>
  <CurrentPublic>
    <Key>SN: 191240234 (SN: 191240234):191240234:Operation.Health</Key>
    <Mean>Ok</Mean>
    <Base>1</Base>
    <Period>300</Period>
    <Timestamp>2023-11-24T08:40:00</Timestamp>
  </CurrentPublic>
  <CurrentPublic>
    <Key>SN: 191240234 (SN: 191240234):191240234:Operation.Evt.Prio</Key>
    <Mean>NonePrio</Mean>
    <Base>1</Base>
    <Period>300</Period>
    <Timestamp>2023-11-24T08:40:00</Timestamp>
  </CurrentPublic>
  <CurrentPublic>
    <Key>SN: 191240234 (SN: 191240234):191240234:Operation.Evt.Msg</Key>
    <Mean>None</Mean>
    <Base>1</Base>
    <Period>300</Period>
    <Timestamp>2023-11-24T08:40:00</Timestamp>
  </CurrentPublic>
  <CurrentPublic>
    <Key>SN: 191246219 (SN: 191246219):191246219:Operation.Health</Key>
    <Mean>Ok</Mean>
    <Base>1</Base>
    <Period>300</Period>
    <Timestamp>2023-11-24T08:40:00</Timestamp>
  </CurrentPublic>
  <CurrentPublic>
    <Key>SN: 191246219 (SN: 191246219):191246219:Operation.Evt.Prio</Key>
    <Mean>NonePrio</Mean>
    <Base>1</Base>
    <Period>300</Period>
    <Timestamp>2023-11-24T08:40:00</Timestamp>
  </CurrentPublic>
  <CurrentPublic>
    <Key>SN: 191246219 (SN: 191246219):191246219:Operation.Evt.Msg</Key>
    <Mean>None</Mean>
    <Base>1</Base>
    <Period>300</Period>
    <Timestamp>2023-11-24T08:40:00</Timestamp>
  </CurrentPublic>
  <CurrentPublic>
    <Key>SN: 191240180 (SN: 191240180):191240180:Operation.Evt.Dsc</Key>
    <Mean>None</Mean>
    <Base>1</Base>
    <Period>300</Period>
    <Timestamp>2023-11-24T08:40:00</Timestamp>
  </CurrentPublic>
  <CurrentPublic>
    <Key>SN: 191240234 (SN: 191240234):191240234:Operation.Evt.Dsc</Key>
    <Mean>None</Mean>
    <Base>1</Base>
    <Period>300</Period>
    <Timestamp>2023-11-24T08:40:00</Timestamp>
  </CurrentPublic>
  <CurrentPublic>
    <Key>SN: 191246219 (SN: 191246219):191246219:Operation.Evt.Dsc</Key>
    <Mean>None</Mean>
    <Base>1</Base>
    <Period>300</Period>
    <Timestamp>2023-11-24T08:40:00</Timestamp>
  </CurrentPublic>
  <CurrentPublic>
    <Key>Cluster Controller:165012367:InOut.AnInA2</Key>
    <Min>0</Min>
    <Max>0</Max>
    <Mean>0</Mean>
    <Base>1</Base>
    <Period>300</Period>
    <Timestamp>2023-11-24T08:40:00</Timestamp>
  </CurrentPublic>
  <CurrentPublic>
    <Key>Cluster Controller:165012367:InOut.AnInA3</Key>
    <Min>0</Min>
    <Max>0</Max>
    <Mean>0</Mean>
    <Base>1</Base>
    <Period>300</Period>
    <Timestamp>2023-11-24T08:40:00</Timestamp>
  </CurrentPublic>
  <CurrentPublic>
    <Key>Cluster Controller:165012367:InOut.AnInVol4</Key>
    <Min>2.07</Min>
    <Max>2.07</Max>
    <Mean>2.07</Mean>
    <Base>1</Base>
    <Period>300</Period>
    <Timestamp>2023-11-24T08:40:00</Timestamp>
  </CurrentPublic>
</ClusterController>